expr/__init__.py
expr/ast.py
expr/builtin.py
expr/core.py
expr/errors.py
expr/grammar.py
expr/parser.py
expr/util.py
expr.py-0.3.0.dist-info/METADATA
expr.py-0.3.0.dist-info/WHEEL
expr.py-0.3.0.dist-info/top_level.txt
expr.py-0.3.0.dist-info/RECORD
