Metadata-Version: 2.1
Name: expr.py
Version: 0.3.0
Summary: A safe and simple math expression evaluator for Python.
Home-page: https://github.com/jay3332/expr.py
Author: jay3332
License: MIT
Project-URL: Issue tracker, https://github.com/jay3332/expr.py/issues
Platform: UNKNOWN
Classifier: License :: OSI Approved :: MIT License
Classifier: Intended Audience :: Developers
Classifier: Natural Language :: English
Classifier: Operating System :: OS Independent
Classifier: Programming Language :: Python :: 3.8
Classifier: Programming Language :: Python :: 3.9
Classifier: Topic :: Software Development :: Libraries
Classifier: Topic :: Software Development :: Libraries :: Python Modules
Classifier: Topic :: Utilities
Classifier: Typing :: Typed
Requires-Python: >=3.8.0
Requires-Dist: rply (>=0.7.8)
